laygo/__init__.py
laygo/errors.py
laygo/helpers.py
laygo/pipeline.py
laygo/transformers/parallel.py
laygo/transformers/transformer.py
laygo-0.1.2.dist-info/METADATA
laygo-0.1.2.dist-info/WHEEL
laygo-0.1.2.dist-info/licenses/LICENSE
laygo-0.1.2.dist-info/RECORD
