Metadata-Version: 2.4
Name: laygo
Version: 0.1.2
Summary: A lightweight Python library for building resilient, in-memory data pipelines with elegant, chainable syntax
Project-URL: Homepage, https://github.com/ringoldsdev/laygo-python
Project-URL: Documentation, https://github.com/ringoldsdev/laygo-python/wiki
Project-URL: Repository, https://github.com/ringoldsdev/laygo-python.git
Project-URL: Issues, https://github.com/ringoldsdev/laygo-python/issues
Author-email: Ringolds Lescinskis <ringolds@lescinskis.com>
License: MIT
License-File: LICENSE
Keywords: chaining,data-processing,etl,functional,pipeline
Classifier: Development Status :: 4 - Beta
Classifier: Intended Audience :: Developers
Classifier: License :: OSI Approved :: MIT License
Classifier: Programming Language :: Python :: 3
Classifier: Programming Language :: Python :: 3.12
Classifier: Programming Language :: Python :: 3.13
Classifier: Topic :: Scientific/Engineering :: Information Analysis
Classifier: Topic :: Software Development :: Libraries :: Python Modules
Classifier: Topic :: Utilities
Classifier: Typing :: Typed
Requires-Python: >=3.12
Provides-Extra: dev
Requires-Dist: pytest>=7.0.0; extra == 'dev'
Requires-Dist: ruff>=0.1.0; extra == 'dev'
Requires-Dist: twine>=4.0.0; extra == 'dev'
